finstack_backend/__init__.py
finstack_backend/auth.py
finstack_backend/constants.py
finstack_backend/models.py
finstack_backend/serializers.py
finstack_backend/two_factor.py
finstack_backend/validation.py
finstack_backend-1.0.5.dist-info/LICENSE
finstack_backend-1.0.5.dist-info/METADATA
finstack_backend-1.0.5.dist-info/WHEEL
finstack_backend-1.0.5.dist-info/top_level.txt
finstack_backend-1.0.5.dist-info/RECORD
